process_snapshot_toolkit/__init__.py
process_snapshot_toolkit/ghidra/__init__.py
process_snapshot_toolkit/ghidra/decompiler.py
process_snapshot_toolkit/snapshot/__init__.py
process_snapshot_toolkit/snapshot/factory.py
process_snapshot_toolkit/snapshot/utils.py
process_snapshot_toolkit/snapshot/v3/__init__.py
process_snapshot_toolkit-0.1.0.data/scripts/ghidra_analyze.py
process_snapshot_toolkit-0.1.0.dist-info/LICENSE.txt
process_snapshot_toolkit-0.1.0.dist-info/METADATA
process_snapshot_toolkit-0.1.0.dist-info/NOTICE.txt
process_snapshot_toolkit-0.1.0.dist-info/WHEEL
process_snapshot_toolkit-0.1.0.dist-info/top_level.txt
process_snapshot_toolkit-0.1.0.dist-info/RECORD
